{
    "metadataAttributes": {
        "player": "Dignified",
        "org": "(+3)",
        "agents": "['skye', 'kayo', 'gekko']",
        "rounds_played": 378,
        "rating": 1.0,
        "average_combat_score": 190.5,
        "kill_deaths": 0.91,
        "kill_assists_survived_traded": "69%",
        "average_damage_per_round": 129.2,
        "kills_per_round": 0.68,
        "assists_per_round": 0.35,
        "first_kills_per_round": 0.06,
        "first_deaths_per_round": 0.05,
        "headshot_percentage": "38%",
        "clutch_success_percentage": "12%",
        "team_id": 15058.0,
        "team_name": "OLD STINKY CAT",
        "agent1": "skye",
        "agent1_use_pct": "(28) 49%",
        "agent1_rounds": 569,
        "agent1_rating": 1.08,
        "agent1_acs": 202.8,
        "agent1_kd": 1.07,
        "agent1_adr": 134.1,
        "agent1_kast": "75%",
        "agent1_kpr": 0.72,
        "agent1_apr": 0.45,
        "agent1_fkpr": 0.07,
        "agent1_fdpr": 0.05,
        "agent1_kills": 412,
        "agent1_deaths": 384,
        "agent1_assists": 256,
        "agent1_fk": 40,
        "agent1_fd": 29,
        "agent2": "kayo",
        "agent2_use_pct": "(17) 30%",
        "agent2_rounds": 361.0,
        "agent2_rating": 1.04,
        "agent2_acs": 194.4,
        "agent2_kd": 0.96,
        "agent2_adr": 126.3,
        "agent2_kast": "75%",
        "agent2_kpr": 0.68,
        "agent2_apr": 0.58,
        "agent2_fkpr": 0.06,
        "agent2_fdpr": 0.07,
        "agent2_kills": 246.0,
        "agent2_deaths": 257.0,
        "agent2_assists": 208.0,
        "agent2_fk": 22.0,
        "agent2_fd": 26.0,
        "agent3": "gekko",
        "agent3_use_pct": "(3) 5%",
        "agent3_rounds": 65.0,
        "agent3_rating": 1.03,
        "agent3_acs": 188.0,
        "agent3_kd": 1.07,
        "agent3_adr": 130.0,
        "agent3_kast": "69%",
        "agent3_kpr": 0.71,
        "agent3_apr": 0.18,
        "agent3_fkpr": 0.02,
        "agent3_fdpr": 0.03,
        "agent3_kills": 46.0,
        "agent3_deaths": 43.0,
        "agent3_assists": 12.0,
        "agent3_fk": 1.0,
        "agent3_fd": 2.0,
        "igl": false,
        "region": "ap",
        "level": "challenger"
    }
}