{
    "metadataAttributes": {
        "player": "sturNN",
        "org": "FB",
        "agents": "['omen', 'cypher', 'killjoy']",
        "rounds_played": 2914,
        "rating": 0.95,
        "average_combat_score": 193.3,
        "kill_deaths": 0.93,
        "kill_assists_survived_traded": "68%",
        "average_damage_per_round": 126.7,
        "kills_per_round": 0.68,
        "assists_per_round": 0.23,
        "first_kills_per_round": 0.07,
        "first_deaths_per_round": 0.08,
        "headshot_percentage": "26%",
        "clutch_success_percentage": "12%",
        "team_id": 5310.0,
        "team_name": "Fenerbah\u00e7e Esports",
        "agent1": "omen",
        "agent1_use_pct": "(67) 26%",
        "agent1_rounds": 1385,
        "agent1_rating": 0.96,
        "agent1_acs": 189.3,
        "agent1_kd": 0.94,
        "agent1_adr": 122.2,
        "agent1_kast": "71%",
        "agent1_kpr": 0.65,
        "agent1_apr": 0.32,
        "agent1_fkpr": 0.06,
        "agent1_fdpr": 0.08,
        "agent1_kills": 904,
        "agent1_deaths": 965,
        "agent1_assists": 445,
        "agent1_fk": 78,
        "agent1_fd": 105,
        "agent2": "killjoy",
        "agent2_use_pct": "(47) 18%",
        "agent2_rounds": 983.0,
        "agent2_rating": 0.94,
        "agent2_acs": 199.6,
        "agent2_kd": 0.92,
        "agent2_adr": 131.7,
        "agent2_kast": "67%",
        "agent2_kpr": 0.68,
        "agent2_apr": 0.19,
        "agent2_fkpr": 0.08,
        "agent2_fdpr": 0.07,
        "agent2_kills": 666.0,
        "agent2_deaths": 725.0,
        "agent2_assists": 183.0,
        "agent2_fk": 77.0,
        "agent2_fd": 70.0,
        "agent3": "viper",
        "agent3_use_pct": "(42) 16%",
        "agent3_rounds": 895.0,
        "agent3_rating": 0.98,
        "agent3_acs": 199.7,
        "agent3_kd": 0.99,
        "agent3_adr": 133.2,
        "agent3_kast": "69%",
        "agent3_kpr": 0.7,
        "agent3_apr": 0.26,
        "agent3_fkpr": 0.07,
        "agent3_fdpr": 0.09,
        "agent3_kills": 624.0,
        "agent3_deaths": 629.0,
        "agent3_assists": 233.0,
        "agent3_fk": 60.0,
        "agent3_fd": 80.0,
        "igl": false,
        "region": "eu",
        "level": "challenger"
    }
}